must_triage/__init__.py
must_triage/cmd.py
must_triage/formatters.py
must_triage/fs.py
must_triage/progress.py
must_triage/inspectors/__init__.py
must_triage/inspectors/base.py
must_triage/inspectors/ocp.py
must_triage/inspectors/ocs.py
must_triage/inspectors/util.py
must_triage-0.3.4.dist-info/AUTHORS
must_triage-0.3.4.dist-info/LICENSE
must_triage-0.3.4.dist-info/METADATA
must_triage-0.3.4.dist-info/WHEEL
must_triage-0.3.4.dist-info/entry_points.txt
must_triage-0.3.4.dist-info/top_level.txt
must_triage-0.3.4.dist-info/RECORD
