Metadata-Version: 2.1
Name: must-triage
Version: 0.3.4
Summary: A utility for triaging must-gather output
Home-page: UNKNOWN
Author: Zack Cerza
Author-email: zack@redhat.com
License: GPLv3
Keywords: python, openshift, ceph
Platform: UNKNOWN
Classifier: Programming Language :: Python :: 3
Classifier: Programming Language :: Python :: 3.7
Classifier: Programming Language :: Python :: 3.8
License-File: LICENSE
License-File: AUTHORS
Requires-Dist: PyYAML
Requires-Dist: tqdm
